cli/__init__.py
cli/commands/__init__.py
cli/commands/find.py
cli/core/__init__.py
cli/core/find.py
cli/core/host/__init__.py
cli/main.py
cli/models/__init__.py
cli/settings.py
cli/utils.py
ncli-0.1.1.dist-info/entry_points.txt
ncli-0.1.1.dist-info/WHEEL
ncli-0.1.1.dist-info/METADATA
ncli-0.1.1.dist-info/RECORD
