Metadata-Version: 2.1
Name: ncli
Version: 0.1.1
Summary: 
Author: Ryan Bradshaw
Author-email: ryan@rbradshaw.dev
Requires-Python: >=3.10,<4.0
Classifier: Programming Language :: Python :: 3
Classifier: Programming Language :: Python :: 3.10
Requires-Dist: httpx (>=0.22.0,<0.23.0)
Requires-Dist: pydantic (>=1.9.0,<2.0.0)
Requires-Dist: python-dotenv (>=0.20.0,<0.21.0)
Requires-Dist: rich (>=12.0.1,<13.0.0)
Requires-Dist: scrapli[full] (>=2022.1.30,<2023.0.0)
Requires-Dist: typer[all] (>=0.4.0,<0.5.0)
